geonames/cli.py
geonames/geonames.py
geonames/lookup_table.py
geonames/__init__.py
geonames-0.1.3.dist-info/DESCRIPTION.rst
geonames-0.1.3.dist-info/entry_points.txt
geonames-0.1.3.dist-info/METADATA
geonames-0.1.3.dist-info/metadata.json
geonames-0.1.3.dist-info/RECORD
geonames-0.1.3.dist-info/top_level.txt
geonames-0.1.3.dist-info/WHEEL
