Metadata-Version: 2.0
Name: geonames
Version: 0.1.3
Summary: Geonames data parser into Shapefile/KML
Home-page: http://addxy.com
Author: Denis Carriere
Author-email: carriere.denis@gmail.com
License: UNKNOWN
Download-URL: https://github.com/DenisCarriere/geonames
Keywords: geonames parser shapefile kml data
Platform: UNKNOWN
Classifier: Development Status :: 5 - Production/Stable
Classifier: Intended Audience :: Developers
Classifier: Intended Audience :: Science/Research
Classifier: License :: OSI Approved :: Apache Software License
Classifier: Natural Language :: English
Classifier: Operating System :: OS Independent
Classifier: Programming Language :: Python :: 2.6
Classifier: Programming Language :: Python :: 2.7
Classifier: Programming Language :: Python :: 3.2
Classifier: Programming Language :: Python :: 3.3
Classifier: Topic :: Internet
Classifier: Topic :: Internet :: WWW/HTTP
Classifier: Topic :: Scientific/Engineering :: GIS
Classifier: Topic :: Software Development :: Libraries :: Python Modules
Requires-Dist: unicodecsv (>=0.9.4)
